{
  "shirts": [
    {
      "id": "1",
      "title": "RAW tee",
      "price": 35.0,
      "menu": [
        { "id": "1",
          "color": "black",
          "button": "../images/black.jpg",
          "img": "../images/mens_shirts/raw1.jpg",
          "frontImg": "https://img1.g-star.com/product/c_fill,f_auto,h_620,q_80/v1560417739/D08512-8415-990-Z01W/g-star-raw-holorn-t-shirt-black.jpg",
          "sideImg": "https://img1.g-star.com/product/c_fill,f_auto,h_550,q_80/v1560417740/D08512-8415-990-Z02W/g-star-raw-holorn-t-shirt-black.jpg",
          "backImg": "https://img1.g-star.com/product/c_fill,f_auto,h_550,q_80/v1560417742/D08512-8415-990-Z03W/g-star-raw-holorn-t-shirt-black.jpg"
        },
        {
          "id": "2",
          "color": "white",
          "button": "../images/white.jpg",
          "img": "../images/mens_shirts/raw_white.jpg",
          "frontImg": "https://img1.g-star.com/product/c_fill,f_auto,h_550,q_80/v1560257416/D08512-8415-110-Z01W/g-star-raw-holorn-t-shirt-white.jpg",
          "sideImg": "https://img1.g-star.com/product/c_fill,f_auto,h_550,q_80/v1560257418/D08512-8415-110-Z02W/g-star-raw-holorn-t-shirt-white.jpg",
          "backImg": "https://img1.g-star.com/product/c_fill,f_auto,h_550,q_80/v1560257421/D08512-8415-110-Z03W/g-star-raw-holorn-t-shirt-white.jpg"
        },
        {
          "id": "3",
          "color": "gray",
          "button": "../images/gray.jpg",
          "img": "../images/mens_shirts/raw_gray.jpg",
          "frontImg": "https://img1.g-star.com/product/c_fill,f_auto,h_550,q_80/v1560257433/D08512-8415-1260-Z01W/g-star-raw-holorn-t-shirt-grey.jpg",
          "sideImg": "https://img1.g-star.com/product/c_fill,f_auto,h_550,q_80/v1560257435/D08512-8415-1260-Z02W/g-star-raw-holorn-t-shirt-grey.jpg",
          "backImg": "https://img1.g-star.com/product/c_fill,f_auto,h_550,q_80/v1560257440/D08512-8415-1260-Z03W/g-star-raw-holorn-t-shirt-grey.jpg"
        },
        {
          "id": "4",
          "color": "dark blue",
          "button": "../images/dark_blue.jpg",
          "img": "../images/mens_shirts/raw_blue.jpg",
          "frontImg": "https://img1.g-star.com/product/c_fill,f_auto,h_550,q_80/v1560417754/D08512-8415-6067-Z01W/g-star-raw-holorn-t-shirt-dark-blue.jpg",
          "sideImg": "https://img1.g-star.com/product/c_fill,f_auto,h_550,q_80/v1560417755/D08512-8415-6067-Z02W/g-star-raw-holorn-t-shirt-dark-blue.jpg",
          "backImg": "https://img1.g-star.com/product/c_fill,f_auto,h_550,q_80/v1560417758/D08512-8415-6067-Z03W/g-star-raw-holorn-t-shirt-dark-blue.jpg"
        }
      ]
    },
    {
      "id": "2",
      "title": "Twin Hearts",
      "price": 95.0,
      "menu": [
        {
          "id": "1",
          "button": "../images/dark_blue.jpg",
          "img": "../images/mens_shirts/twin_heart.jpeg",
          "color": "dark blue",
          "frontImg": "https://n.nordstrommedia.com/id/sr3/fb064f61-0c8b-47b1-834b-7794dda660c1.jpeg?crop=pad&pad_color=FFF&format=jpeg&w=780&h=1196&dpr=2&quality=60",
          "sideImg": "https://n.nordstrommedia.com/id/sr3/657b6ec4-c879-4fd0-abe8-a101a2051422.jpeg?crop=pad&pad_color=FFF&format=jpeg&w=780&h=1196&dpr=2&quality=60",
          "backImg": "https://n.nordstrommedia.com/id/sr3/baa9fd51-4039-4cc5-8b31-f287ac768d92.jpeg?crop=pad&pad_color=FFF&format=jpeg&w=780&h=1196&dpr=2&quality=60"
        },
        {
          "id": "2",
          "button": "../images/black.jpg",
          "img": "../images/mens_shirts/twin_heart_black.jpeg",
          "color": "black",
          "frontImg": "https://n.nordstrommedia.com/id/sr3/31adb74d-4578-41d6-a20a-0ae2f99aba3d.jpeg?crop=pad&pad_color=FFF&format=jpeg&w=780&h=1196&dpr=2&quality=60",
          "sideImg": "https://n.nordstrommedia.com/id/sr3/456ee247-037b-4f9e-82ae-8857975e0e05.jpeg?crop=pad&pad_color=FFF&format=jpeg&w=780&h=1196&dpr=2&quality=60",
          "backImg": "https://n.nordstrommedia.com/id/sr3/6eaa5b0a-2bbc-4b4c-82dc-7a128eae4737.jpeg?crop=pad&pad_color=FFF&format=jpeg&w=780&h=1196&dpr=2&quality=60"
        }
      ]
    },
    {
      "id": "3",
      "title": "Single Hearts",
      "price": 95.0,
      "menu": [
        {
          "id": "1",
          "button": "../images/white.jpg",
          "img": "../images/mens_shirts/white_heart.jpeg"
        }
      ]
    },
    {
      "id": "4",
      "title": "Basic Tee",
      "price": 65.0,
      "menu": [
        {
          "id": "1",
          "button": "../images/black.jpg",
          "img": "../images/mens_shirts/basic_black_round.jpg"
        },
        {
          "id": "2",
          "button": "../images/white.jpg",
          "img": "../images/mens_shirts/basic_white_round.jpg"
        },
        {
          "id": "3",
          "button": "../images/gray.jpg",
          "img": "../images/mens_shirts/basic_gray_round.jpg"
        }
      ]
    },
    {
      "id": "5",
      "title": "Belly Sky",
      "price": 85.0,
      "menu": [
        {
          "id": "1",
          "button": "../images/yellow.png",
          "img": "../images/mens_shirts/belly_sky_yellow.jpeg"
        },
        {
          "id": "2",
          "button": "../images/red.png",
          "img": "../images/mens_shirts/belly_sky_red.jpeg"
        },
        {
          "id": "3",
          "button": "../images/purple.png",
          "img": "../images/mens_shirts/belly_sky_purple.jpeg"
        }
      ]
    },
    {
      "id": "6",
      "title": "Slim Fit Henley",
      "price": 105.0,
      "menu": [
        {
          "id": "1",
          "button": "../images/blue.png",
          "img": "../images/mens_shirts/slim_fit_henley_blue.jpeg"
        },
        {
          "id": "2",
          "button": "../images/blue_iron.png",
          "img": "../images/mens_shirts/slim_fit_henley_blue_iron.jpeg"
        }
      ]
    }
  ],
  "hoodies": [
    {
      "id": "7",
      "title": "Basic Black Hoodie",
      "price": 110.00,
      "menu": [
        { "id": "1", "button": "../images/black.jpg", "img": "../images/mens_hoodies/basic_black_hoodie.jpeg" },
        { "id": "2", "button": "../images/mocha.png", "img": "../images/mens_hoodies/basic_mocha_hoodie.jpeg" },
        { "id": "3", "button": "../images/volt.png", "img": "../images/mens_hoodies/basic_volt_hoodie.jpeg" }
      ]
    },
    {
      "id": "8",
      "title": "ACNE Black Hoodie",
      "price": 150.00,
      "menu": [
        {  "id": "1", "button": "../images/black.jpg", "img": "../images/mens_hoodies/acne_hoodie.jpeg" }
      ]
    }
  ],
  "sunglasses": [
    {
      "id": "9",
      "title": "Ray Ban \"Boyfriends\"",
      "price": 210.00,
      "menu": [
        { "id": "1", "button": "../images/rb_black.png", "img": "../images/mens_sunglasses/rb_bf_black.jpeg" },
        { "id": "2", "button": "../images/rb_brown.png", "img": "../images/mens_sunglasses/rb_bf_brown.jpeg" }
      ]
    }]
}

